sefaria_jewish_library/__init__.py
sefaria_jewish_library/demo.py
sefaria_jewish_library/sefaria_handler.py
sefaria_jewish_library/server.py
iflow_mcp_sefaria_jewish_library-0.1.0.dist-info/METADATA
iflow_mcp_sefaria_jewish_library-0.1.0.dist-info/WHEEL
iflow_mcp_sefaria_jewish_library-0.1.0.dist-info/entry_points.txt
iflow_mcp_sefaria_jewish_library-0.1.0.dist-info/licenses/LICENSE
iflow_mcp_sefaria_jewish_library-0.1.0.dist-info/RECORD
