Metadata-Version: 2.4
Name: iflow-mcp_sefaria_jewish_library
Version: 0.1.0
Summary: the jewish library, accessible to LLMs 
License-File: LICENSE
Requires-Python: >=3.12
Requires-Dist: mcp>=1.3.0
Requires-Dist: requests
